dash_echarts/Chart.py
dash_echarts/DashECharts.py
dash_echarts/__init__.py
dash_echarts/_imports_.py
dash_echarts/dash_echarts.min.js
dash_echarts/dash_echarts.min.js.map
dash_echarts/metadata.json
dash_echarts/package-info.json
dash_echarts/examples/__init__.py
dash_echarts/examples/air.py
dash_echarts/examples/am.py
dash_echarts/examples/am2.py
dash_echarts/examples/bar.py
dash_echarts/examples/bar_race.py
dash_echarts/examples/bar_style.py
dash_echarts/examples/china.json
dash_echarts/examples/custom_profit.py
dash_echarts/examples/heat.py
dash_echarts/examples/hist_bar.py
dash_echarts/examples/life-expectancy-table.json
dash_echarts/examples/line.py
dash_echarts/examples/line_race.py
dash_echarts/examples/map.py
dash_echarts/examples/play.py
dash_echarts/examples/regression.py
dash_echarts/examples/scatter3d.py
dash_echarts/examples/assets/responsive-sidebar.css
dash_echarts/examples/gallery/__init__.py
dash_echarts/examples/gallery/bar_basic.py
dash_echarts/examples/gallery/bar_horizontal_stacked.py
dash_echarts/examples/gallery/bar_race.py
dash_echarts/examples/gallery/bar_style.py
dash_echarts/examples/gallery/bar_waterfall.py
dash_echarts/examples/gallery/line_area_basic.py
dash_echarts/examples/gallery/line_area_stacked.py
dash_echarts/examples/gallery/line_basic.py
dash_echarts/examples/gallery/line_race.py
dash_echarts/examples/gallery/line_stacked.py
dash_echarts/examples/gallery/main.py
dash_echarts/examples/static/china.json
dash_echarts/examples/static/dash_echarts_line.gif
dash_echarts/examples/static/life-expectancy-table.json
dash_echarts/examples/static/responsive-sidebar.css
dash_echarts-0.0.12.8.dist-info/LICENSE
dash_echarts-0.0.12.8.dist-info/METADATA
dash_echarts-0.0.12.8.dist-info/WHEEL
dash_echarts-0.0.12.8.dist-info/entry_points.txt
dash_echarts-0.0.12.8.dist-info/top_level.txt
dash_echarts-0.0.12.8.dist-info/RECORD
