Metadata-Version: 2.1
Name: dash-echarts
Version: 0.0.12.8
Summary: echarts for dash
Home-page: UNKNOWN
Author: dameng
Author-email: <pingf0@gmail.com>
License: MIT
Platform: UNKNOWN
Classifier: Framework :: Dash
Requires-Dist: dash
Provides-Extra: play
Requires-Dist: dash-bootstrap-components ; extra == 'play'
Requires-Dist: dash-tabulator ; extra == 'play'
Requires-Dist: dash-extensions ; extra == 'play'
